syntactic/__init__.py
syntactic/__main__.py
syntactic/app.py
syntactic/cli.py
syntactic/examples/__syntax__.py
syntactic_installer.pth
syntactic-0.1.3.dist-info/entry_points.txt
syntactic-0.1.3.dist-info/LICENSE
syntactic-0.1.3.dist-info/WHEEL
syntactic-0.1.3.dist-info/METADATA
syntactic-0.1.3.dist-info/RECORD
