Metadata-Version: 2.1
Name: syntactic
Version: 0.1.3
Summary: Custom syntax for Python.
Author: Metatooling
Author-email: metatooling@cordaz.com
Requires-Python: >=3.6,<4.0
Classifier: Programming Language :: Python :: 3
Classifier: Programming Language :: Python :: 3.6
Classifier: Programming Language :: Python :: 3.7
Classifier: Programming Language :: Python :: 3.8
Provides-Extra: cli
Provides-Extra: docs
Requires-Dist: importlib_metadata
